unimate/__init__.py
UniMator-0.0.1.dist-info/METADATA
UniMator-0.0.1.dist-info/WHEEL
UniMator-0.0.1.dist-info/top_level.txt
UniMator-0.0.1.dist-info/RECORD
