Metadata-Version: 2.1
Name: UniMator
Version: 0.0.1
Summary: use import unimate to import
Home-page: UNKNOWN
Author: WebSoft-tech
Author-email: 
License: UNKNOWN
Platform: UNKNOWN
Classifier: Programming Language :: Python :: 3
Classifier: License :: OSI Approved :: MIT License
Classifier: Operating System :: Microsoft :: Windows :: Windows 10
Requires-Python: >=3.6
